<?xml version="1.0"?>
<ArchiveTransfer><ArchiveUnit><DataObject><URI>D:\wamp64\www\TestSEDA\Fichierarchive/Lettre de Motivation Djibril.pdf</URI></DataObject><DescriptiveMetadata><Content><Titre>ddd</Titre><Description>ddd</Description><Couverture>ddd</Couverture><MotCle>ddd</MotCle><AuthorizedAgent><NomAgent>ddd</NomAgent></AuthorizedAgent><DescriptionLevel>Item</DescriptionLevel><TypeDoc>.pdf</TypeDoc><OriginatingAgency>Originating Agency</OriginatingAgency><SubmissionAgency>Submission Agency</SubmissionAgency></Content></DescriptiveMetadata><ProfileArchive>ddd</ProfileArchive></ArchiveUnit></ArchiveTransfer>
